[
    {
        "_id": "642fdff355cc905f2e46c46b",
        "name": "Solis Castro",
        "price": 500
    },
    {
        "_id": "642fdff334d48f95f53452ff",
        "name": "Webb Mack",
        "price": 500
    },
    {
        "_id": "642fdff36bbbeabc0015ad36",
        "name": "Reese Holland",
        "price": 500
    },
    {
        "_id": "642fdff3884eb5748f5a1403",
        "name": "Duran Whitley",
        "price": 500
    },
    {
        "_id": "642fdff33c9fd5dcf2b24ae8",
        "name": "Lancaster Steele",
        "price": 500
    },
    {
        "_id": "642fdff3bf317798c5d50c2b",
        "name": "Ivy Gregory",
        "price": 500
    },
    {
        "_id": "642fdff361b19d5a4c947623",
        "name": "Howard Beard",
        "price": 500
    },
    {
        "_id": "642fdff35c408c717d7c5cad",
        "name": "Daisy Griffin",
        "price": 500
    },
    {
        "_id": "642fdff307646aa32fa984e8",
        "name": "Cummings Shannon",
        "price": 500
    },
    {
        "_id": "642fdff349112afc92d3748d",
        "name": "Adrienne Fisher",
        "price": 500
    }
]